<annotation>
  <folder>fork png</folder>
  <filename>fork_371.png</filename>
  <path>fork_371.png</path>
  <source>
    <database>Unknown</database>
  </source>
  <size>
    <width>128</width>
    <height>128</height>
    <depth>3</depth>
  </size>
  <segmented>0</segmented>
  <object>
    <name>fork</name>
    <pose>Unspecified</pose>
    <truncated>1</truncated>
    <difficult>0</difficult>
    <bndbox>
      <xmin>5</xmin>
      <ymin>11</ymin>
      <xmax>80</xmax>
      <ymax>128</ymax>
    </bndbox>
  </object>
</annotation>