<annotation>
	<folder>fork png</folder>
	<filename>fork_original_4AD4NXJSM7PZ.png_fc4aadba-7f7f-422c-afbd-980c4334d6b0.png</filename>
	<path>C:\Users\OM\Desktop\SEM 6\PBL 2\fork png\fork_original_4AD4NXJSM7PZ.png_fc4aadba-7f7f-422c-afbd-980c4334d6b0.png</path>
	<source>
		<database>Unknown</database>
	</source>
	<size>
		<width>128</width>
		<height>128</height>
		<depth>3</depth>
	</size>
	<segmented>0</segmented>
	<object>
		<name>Fork</name>
		<pose>Unspecified</pose>
		<truncated>1</truncated>
		<difficult>0</difficult>
		<bndbox>
			<xmin>4</xmin>
			<ymin>42</ymin>
			<xmax>128</xmax>
			<ymax>78</ymax>
		</bndbox>
	</object>
</annotation>
