<annotation>
	<folder>sd_final</folder>
	<filename>png_original_screwdriver_48.png_4bba1d08-1122-44a2-a822-99b04cd42b27.png</filename>
	<path>C:\Users\OM\Desktop\SEM 6\PBL 2\screwdriver\sd_final\png_original_screwdriver_48.png_4bba1d08-1122-44a2-a822-99b04cd42b27.png</path>
	<source>
		<database>Unknown</database>
	</source>
	<size>
		<width>319</width>
		<height>158</height>
		<depth>3</depth>
	</size>
	<segmented>0</segmented>
	<object>
		<name>Screwdriver</name>
		<pose>Unspecified</pose>
		<truncated>0</truncated>
		<difficult>0</difficult>
		<bndbox>
			<xmin>26</xmin>
			<ymin>46</ymin>
			<xmax>307</xmax>
			<ymax>124</ymax>
		</bndbox>
	</object>
</annotation>
